[
  {
    "rank": 1,
    "trial_num": 596,
    "trial_id": 28338,
    "fitness_sharpe": 0.3584218894549178,
    "parameters": {
      "buy_threshold": 36.0,
      "rsi_period": 19.0,
      "sell_threshold": 61.0
    },
    "training_metrics": null,
    "testing_metrics": null
  },
  {
    "rank": 2,
    "trial_num": 600,
    "trial_id": 28342,
    "fitness_sharpe": 0.3584218894549178,
    "parameters": {
      "buy_threshold": 36.0,
      "rsi_period": 19.0,
      "sell_threshold": 61.0
    },
    "training_metrics": {
      "total": 10,
      "total_winning_trades": 9,
      "total_losing_trades": 1,
      "starting_balance": 10000.0,
      "finishing_balance": 12238.21134165,
      "win_rate": 0.9,
      "ratio_avg_win_loss": 1.7692199376321707,
      "longs_count": 10,
      "longs_percentage": 100.0,
      "shorts_percentage": 0.0,
      "shorts_count": 0,
      "fee": 113.15175835000001,
      "net_profit": 2238.211341650002,
      "net_profit_percentage": 22.38211341650002,
      "average_win": 265.355061738889,
      "average_loss": 149.98421399999935,
      "expectancy": 223.82113416500016,
      "expectancy_percentage": 2.238211341650002,
      "expected_net_profit_every_100_trades": 223.8211341650002,
      "average_holding_period": 154440.0,
      "average_winning_holding_period": 130800.0,
      "average_losing_holding_period": 367200.0,
      "gross_profit": 2388.195555650001,
      "gross_loss": -149.98421399999935,
      "max_drawdown": -3.8423573817650047,
      "annual_return": 50.616484697713446,
      "sharpe_ratio": 3.442640784004096,
      "calmar_ratio": 13.17328912139415,
      "sortino_ratio": 7.534542803810113,
      "omega_ratio": 5.009518767376441,
      "serenity_index": Infinity,
      "total_open_trades": 0,
      "open_pl": 0.0,
      "winning_streak": 9,
      "losing_streak": 1,
      "largest_losing_trade": -149.98421399999935,
      "largest_winning_trade": 478.662306150002,
      "current_streak": -1
    },
    "testing_metrics": {
      "total": 2,
      "total_winning_trades": 2,
      "total_losing_trades": 0,
      "starting_balance": 10000.0,
      "finishing_balance": 10210.421151299997,
      "win_rate": 1.0,
      "ratio_avg_win_loss": NaN,
      "longs_count": 2,
      "longs_percentage": 100.0,
      "shorts_percentage": 0.0,
      "shorts_count": 0,
      "fee": 19.996448700000002,
      "net_profit": 210.421151300002,
      "net_profit_percentage": 2.10421151300002,
      "average_win": 105.210575650001,
      "average_loss": NaN,
      "expectancy": 105.210575650001,
      "expectancy_percentage": 1.05210575650001,
      "expected_net_profit_every_100_trades": 105.210575650001,
      "average_holding_period": 147600.0,
      "average_winning_holding_period": 147600.0,
      "average_losing_holding_period": NaN,
      "gross_profit": 210.421151300002,
      "gross_loss": 0.0,
      "max_drawdown": 0.0,
      "annual_return": 8.71112858289187,
      "sharpe_ratio": 3.5148845561838433,
      "calmar_ratio": 0.0,
      "sortino_ratio": Infinity,
      "omega_ratio": NaN,
      "serenity_index": Infinity,
      "total_open_trades": 0,
      "open_pl": 0.0,
      "winning_streak": 2,
      "losing_streak": 0,
      "largest_losing_trade": 0.0,
      "largest_winning_trade": 165.18696850000174,
      "current_streak": 2
    }
  },
  {
    "rank": 3,
    "trial_num": 488,
    "trial_id": 28230,
    "fitness_sharpe": 0.35163567882995905,
    "parameters": {
      "buy_threshold": 35.0,
      "rsi_period": 17.0,
      "sell_threshold": 62.0
    },
    "training_metrics": null,
    "testing_metrics": null
  },
  {
    "rank": 4,
    "trial_num": 490,
    "trial_id": 28232,
    "fitness_sharpe": 0.35163567882995905,
    "parameters": {
      "buy_threshold": 35.0,
      "rsi_period": 17.0,
      "sell_threshold": 62.0
    },
    "training_metrics": null,
    "testing_metrics": null
  },
  {
    "rank": 5,
    "trial_num": 492,
    "trial_id": 28234,
    "fitness_sharpe": 0.35163567882995905,
    "parameters": {
      "buy_threshold": 35.0,
      "rsi_period": 17.0,
      "sell_threshold": 62.0
    },
    "training_metrics": null,
    "testing_metrics": null
  },
  {
    "rank": 6,
    "trial_num": 495,
    "trial_id": 28237,
    "fitness_sharpe": 0.35163567882995905,
    "parameters": {
      "buy_threshold": 35.0,
      "rsi_period": 17.0,
      "sell_threshold": 62.0
    },
    "training_metrics": {
      "total": 10,
      "total_winning_trades": 9,
      "total_losing_trades": 1,
      "starting_balance": 10000.0,
      "finishing_balance": 12194.01620355,
      "win_rate": 0.9,
      "ratio_avg_win_loss": 1.7364793526796753,
      "longs_count": 10,
      "longs_percentage": 100.0,
      "shorts_percentage": 0.0,
      "shorts_count": 0,
      "fee": 113.51749645000001,
      "net_profit": 2194.01620355,
      "net_profit_percentage": 21.940162035499995,
      "average_win": 260.4444908388888,
      "average_loss": 149.98421399999935,
      "expectancy": 219.40162035499998,
      "expectancy_percentage": 2.19401620355,
      "expected_net_profit_every_100_trades": 219.401620355,
      "average_holding_period": 149400.0,
      "average_winning_holding_period": 125200.0,
      "average_losing_holding_period": 367200.0,
      "gross_profit": 2344.000417549999,
      "gross_loss": -149.98421399999935,
      "max_drawdown": -3.856114146944245,
      "annual_return": 49.51559771199461,
      "sharpe_ratio": 3.3679924671295494,
      "calmar_ratio": 12.84080186039953,
      "sortino_ratio": 7.37677173104235,
      "omega_ratio": 4.926230726658691,
      "serenity_index": Infinity,
      "total_open_trades": 0,
      "open_pl": 0.0,
      "winning_streak": 9,
      "losing_streak": 1,
      "largest_losing_trade": -149.98421399999935,
      "largest_winning_trade": 500.20492945000166,
      "current_streak": -1
    },
    "testing_metrics": {
      "total": 3,
      "total_winning_trades": 2,
      "total_losing_trades": 1,
      "starting_balance": 10000.0,
      "finishing_balance": 9962.935304999997,
      "win_rate": 0.6666666666666666,
      "ratio_avg_win_loss": 0.42511754600489654,
      "longs_count": 3,
      "longs_percentage": 100.0,
      "shorts_percentage": 0.0,
      "shorts_count": 0,
      "fee": 29.972295000000003,
      "net_profit": -37.06469499999798,
      "net_profit_percentage": -0.3706469499999798,
      "average_win": 105.210575650001,
      "average_loss": 247.4858463,
      "expectancy": -12.354898333332685,
      "expectancy_percentage": -0.12354898333332685,
      "expected_net_profit_every_100_trades": -12.354898333332685,
      "average_holding_period": 241200.0,
      "average_winning_holding_period": 147600.0,
      "average_losing_holding_period": 428400.0,
      "gross_profit": 210.421151300002,
      "gross_loss": -247.4858463,
      "max_drawdown": -3.333994706052401,
      "annual_return": -1.4783857643808407,
      "sharpe_ratio": -0.26211956595073843,
      "calmar_ratio": -0.4434277480096288,
      "sortino_ratio": -0.32964650024319886,
      "omega_ratio": 0.8996324367154944,
      "serenity_index": -Infinity,
      "total_open_trades": 0,
      "open_pl": 0.0,
      "winning_streak": 2,
      "losing_streak": 1,
      "largest_losing_trade": -247.4858463,
      "largest_winning_trade": 165.18696850000174,
      "current_streak": -1
    }
  },
  {
    "rank": 7,
    "trial_num": 497,
    "trial_id": 28239,
    "fitness_sharpe": 0.35163567882995905,
    "parameters": {
      "buy_threshold": 35.0,
      "rsi_period": 17.0,
      "sell_threshold": 62.0
    },
    "training_metrics": {
      "total": 10,
      "total_winning_trades": 9,
      "total_losing_trades": 1,
      "starting_balance": 10000.0,
      "finishing_balance": 12194.01620355,
      "win_rate": 0.9,
      "ratio_avg_win_loss": 1.7364793526796753,
      "longs_count": 10,
      "longs_percentage": 100.0,
      "shorts_percentage": 0.0,
      "shorts_count": 0,
      "fee": 113.51749645000001,
      "net_profit": 2194.01620355,
      "net_profit_percentage": 21.940162035499995,
      "average_win": 260.4444908388888,
      "average_loss": 149.98421399999935,
      "expectancy": 219.40162035499998,
      "expectancy_percentage": 2.19401620355,
      "expected_net_profit_every_100_trades": 219.401620355,
      "average_holding_period": 149400.0,
      "average_winning_holding_period": 125200.0,
      "average_losing_holding_period": 367200.0,
      "gross_profit": 2344.000417549999,
      "gross_loss": -149.98421399999935,
      "max_drawdown": -3.856114146944245,
      "annual_return": 49.51559771199461,
      "sharpe_ratio": 3.3679924671295494,
      "calmar_ratio": 12.84080186039953,
      "sortino_ratio": 7.37677173104235,
      "omega_ratio": 4.926230726658691,
      "serenity_index": Infinity,
      "total_open_trades": 0,
      "open_pl": 0.0,
      "winning_streak": 9,
      "losing_streak": 1,
      "largest_losing_trade": -149.98421399999935,
      "largest_winning_trade": 500.20492945000166,
      "current_streak": -1
    },
    "testing_metrics": {
      "total": 3,
      "total_winning_trades": 2,
      "total_losing_trades": 1,
      "starting_balance": 10000.0,
      "finishing_balance": 9962.935304999997,
      "win_rate": 0.6666666666666666,
      "ratio_avg_win_loss": 0.42511754600489654,
      "longs_count": 3,
      "longs_percentage": 100.0,
      "shorts_percentage": 0.0,
      "shorts_count": 0,
      "fee": 29.972295000000003,
      "net_profit": -37.06469499999798,
      "net_profit_percentage": -0.3706469499999798,
      "average_win": 105.210575650001,
      "average_loss": 247.4858463,
      "expectancy": -12.354898333332685,
      "expectancy_percentage": -0.12354898333332685,
      "expected_net_profit_every_100_trades": -12.354898333332685,
      "average_holding_period": 241200.0,
      "average_winning_holding_period": 147600.0,
      "average_losing_holding_period": 428400.0,
      "gross_profit": 210.421151300002,
      "gross_loss": -247.4858463,
      "max_drawdown": -3.333994706052401,
      "annual_return": -1.4783857643808407,
      "sharpe_ratio": -0.26211956595073843,
      "calmar_ratio": -0.4434277480096288,
      "sortino_ratio": -0.32964650024319886,
      "omega_ratio": 0.8996324367154944,
      "serenity_index": -Infinity,
      "total_open_trades": 0,
      "open_pl": 0.0,
      "winning_streak": 2,
      "losing_streak": 1,
      "largest_losing_trade": -247.4858463,
      "largest_winning_trade": 165.18696850000174,
      "current_streak": -1
    }
  },
  {
    "rank": 8,
    "trial_num": 499,
    "trial_id": 28241,
    "fitness_sharpe": 0.35163567882995905,
    "parameters": {
      "buy_threshold": 35.0,
      "rsi_period": 17.0,
      "sell_threshold": 62.0
    },
    "training_metrics": {
      "total": 10,
      "total_winning_trades": 9,
      "total_losing_trades": 1,
      "starting_balance": 10000.0,
      "finishing_balance": 12194.01620355,
      "win_rate": 0.9,
      "ratio_avg_win_loss": 1.7364793526796753,
      "longs_count": 10,
      "longs_percentage": 100.0,
      "shorts_percentage": 0.0,
      "shorts_count": 0,
      "fee": 113.51749645000001,
      "net_profit": 2194.01620355,
      "net_profit_percentage": 21.940162035499995,
      "average_win": 260.4444908388888,
      "average_loss": 149.98421399999935,
      "expectancy": 219.40162035499998,
      "expectancy_percentage": 2.19401620355,
      "expected_net_profit_every_100_trades": 219.401620355,
      "average_holding_period": 149400.0,
      "average_winning_holding_period": 125200.0,
      "average_losing_holding_period": 367200.0,
      "gross_profit": 2344.000417549999,
      "gross_loss": -149.98421399999935,
      "max_drawdown": -3.856114146944245,
      "annual_return": 49.51559771199461,
      "sharpe_ratio": 3.3679924671295494,
      "calmar_ratio": 12.84080186039953,
      "sortino_ratio": 7.37677173104235,
      "omega_ratio": 4.926230726658691,
      "serenity_index": Infinity,
      "total_open_trades": 0,
      "open_pl": 0.0,
      "winning_streak": 9,
      "losing_streak": 1,
      "largest_losing_trade": -149.98421399999935,
      "largest_winning_trade": 500.20492945000166,
      "current_streak": -1
    },
    "testing_metrics": {
      "total": 3,
      "total_winning_trades": 2,
      "total_losing_trades": 1,
      "starting_balance": 10000.0,
      "finishing_balance": 9962.935304999997,
      "win_rate": 0.6666666666666666,
      "ratio_avg_win_loss": 0.42511754600489654,
      "longs_count": 3,
      "longs_percentage": 100.0,
      "shorts_percentage": 0.0,
      "shorts_count": 0,
      "fee": 29.972295000000003,
      "net_profit": -37.06469499999798,
      "net_profit_percentage": -0.3706469499999798,
      "average_win": 105.210575650001,
      "average_loss": 247.4858463,
      "expectancy": -12.354898333332685,
      "expectancy_percentage": -0.12354898333332685,
      "expected_net_profit_every_100_trades": -12.354898333332685,
      "average_holding_period": 241200.0,
      "average_winning_holding_period": 147600.0,
      "average_losing_holding_period": 428400.0,
      "gross_profit": 210.421151300002,
      "gross_loss": -247.4858463,
      "max_drawdown": -3.333994706052401,
      "annual_return": -1.4783857643808407,
      "sharpe_ratio": -0.26211956595073843,
      "calmar_ratio": -0.4434277480096288,
      "sortino_ratio": -0.32964650024319886,
      "omega_ratio": 0.8996324367154944,
      "serenity_index": -Infinity,
      "total_open_trades": 0,
      "open_pl": 0.0,
      "winning_streak": 2,
      "losing_streak": 1,
      "largest_losing_trade": -247.4858463,
      "largest_winning_trade": 165.18696850000174,
      "current_streak": -1
    }
  },
  {
    "rank": 9,
    "trial_num": 514,
    "trial_id": 28256,
    "fitness_sharpe": 0.35163567882995905,
    "parameters": {
      "buy_threshold": 35.0,
      "rsi_period": 17.0,
      "sell_threshold": 62.0
    },
    "training_metrics": null,
    "testing_metrics": null
  },
  {
    "rank": 10,
    "trial_num": 518,
    "trial_id": 28260,
    "fitness_sharpe": 0.35163567882995905,
    "parameters": {
      "buy_threshold": 35.0,
      "rsi_period": 17.0,
      "sell_threshold": 62.0
    },
    "training_metrics": null,
    "testing_metrics": null
  },
  {
    "rank": 11,
    "trial_num": 520,
    "trial_id": 28262,
    "fitness_sharpe": 0.35163567882995905,
    "parameters": {
      "buy_threshold": 35.0,
      "rsi_period": 17.0,
      "sell_threshold": 62.0
    },
    "training_metrics": null,
    "testing_metrics": null
  },
  {
    "rank": 12,
    "trial_num": 521,
    "trial_id": 28263,
    "fitness_sharpe": 0.35163567882995905,
    "parameters": {
      "buy_threshold": 35.0,
      "rsi_period": 17.0,
      "sell_threshold": 62.0
    },
    "training_metrics": {
      "total": 10,
      "total_winning_trades": 9,
      "total_losing_trades": 1,
      "starting_balance": 10000.0,
      "finishing_balance": 12194.01620355,
      "win_rate": 0.9,
      "ratio_avg_win_loss": 1.7364793526796753,
      "longs_count": 10,
      "longs_percentage": 100.0,
      "shorts_percentage": 0.0,
      "shorts_count": 0,
      "fee": 113.51749645000001,
      "net_profit": 2194.01620355,
      "net_profit_percentage": 21.940162035499995,
      "average_win": 260.4444908388888,
      "average_loss": 149.98421399999935,
      "expectancy": 219.40162035499998,
      "expectancy_percentage": 2.19401620355,
      "expected_net_profit_every_100_trades": 219.401620355,
      "average_holding_period": 149400.0,
      "average_winning_holding_period": 125200.0,
      "average_losing_holding_period": 367200.0,
      "gross_profit": 2344.000417549999,
      "gross_loss": -149.98421399999935,
      "max_drawdown": -3.856114146944245,
      "annual_return": 49.51559771199461,
      "sharpe_ratio": 3.3679924671295494,
      "calmar_ratio": 12.84080186039953,
      "sortino_ratio": 7.37677173104235,
      "omega_ratio": 4.926230726658691,
      "serenity_index": Infinity,
      "total_open_trades": 0,
      "open_pl": 0.0,
      "winning_streak": 9,
      "losing_streak": 1,
      "largest_losing_trade": -149.98421399999935,
      "largest_winning_trade": 500.20492945000166,
      "current_streak": -1
    },
    "testing_metrics": {
      "total": 3,
      "total_winning_trades": 2,
      "total_losing_trades": 1,
      "starting_balance": 10000.0,
      "finishing_balance": 9962.935304999997,
      "win_rate": 0.6666666666666666,
      "ratio_avg_win_loss": 0.42511754600489654,
      "longs_count": 3,
      "longs_percentage": 100.0,
      "shorts_percentage": 0.0,
      "shorts_count": 0,
      "fee": 29.972295000000003,
      "net_profit": -37.06469499999798,
      "net_profit_percentage": -0.3706469499999798,
      "average_win": 105.210575650001,
      "average_loss": 247.4858463,
      "expectancy": -12.354898333332685,
      "expectancy_percentage": -0.12354898333332685,
      "expected_net_profit_every_100_trades": -12.354898333332685,
      "average_holding_period": 241200.0,
      "average_winning_holding_period": 147600.0,
      "average_losing_holding_period": 428400.0,
      "gross_profit": 210.421151300002,
      "gross_loss": -247.4858463,
      "max_drawdown": -3.333994706052401,
      "annual_return": -1.4783857643808407,
      "sharpe_ratio": -0.26211956595073843,
      "calmar_ratio": -0.4434277480096288,
      "sortino_ratio": -0.32964650024319886,
      "omega_ratio": 0.8996324367154944,
      "serenity_index": -Infinity,
      "total_open_trades": 0,
      "open_pl": 0.0,
      "winning_streak": 2,
      "losing_streak": 1,
      "largest_losing_trade": -247.4858463,
      "largest_winning_trade": 165.18696850000174,
      "current_streak": -1
    }
  },
  {
    "rank": 13,
    "trial_num": 525,
    "trial_id": 28267,
    "fitness_sharpe": 0.35163567882995905,
    "parameters": {
      "buy_threshold": 35.0,
      "rsi_period": 17.0,
      "sell_threshold": 62.0
    },
    "training_metrics": {
      "total": 10,
      "total_winning_trades": 9,
      "total_losing_trades": 1,
      "starting_balance": 10000.0,
      "finishing_balance": 12194.01620355,
      "win_rate": 0.9,
      "ratio_avg_win_loss": 1.7364793526796753,
      "longs_count": 10,
      "longs_percentage": 100.0,
      "shorts_percentage": 0.0,
      "shorts_count": 0,
      "fee": 113.51749645000001,
      "net_profit": 2194.01620355,
      "net_profit_percentage": 21.940162035499995,
      "average_win": 260.4444908388888,
      "average_loss": 149.98421399999935,
      "expectancy": 219.40162035499998,
      "expectancy_percentage": 2.19401620355,
      "expected_net_profit_every_100_trades": 219.401620355,
      "average_holding_period": 149400.0,
      "average_winning_holding_period": 125200.0,
      "average_losing_holding_period": 367200.0,
      "gross_profit": 2344.000417549999,
      "gross_loss": -149.98421399999935,
      "max_drawdown": -3.856114146944245,
      "annual_return": 49.51559771199461,
      "sharpe_ratio": 3.3679924671295494,
      "calmar_ratio": 12.84080186039953,
      "sortino_ratio": 7.37677173104235,
      "omega_ratio": 4.926230726658691,
      "serenity_index": Infinity,
      "total_open_trades": 0,
      "open_pl": 0.0,
      "winning_streak": 9,
      "losing_streak": 1,
      "largest_losing_trade": -149.98421399999935,
      "largest_winning_trade": 500.20492945000166,
      "current_streak": -1
    },
    "testing_metrics": {
      "total": 3,
      "total_winning_trades": 2,
      "total_losing_trades": 1,
      "starting_balance": 10000.0,
      "finishing_balance": 9962.935304999997,
      "win_rate": 0.6666666666666666,
      "ratio_avg_win_loss": 0.42511754600489654,
      "longs_count": 3,
      "longs_percentage": 100.0,
      "shorts_percentage": 0.0,
      "shorts_count": 0,
      "fee": 29.972295000000003,
      "net_profit": -37.06469499999798,
      "net_profit_percentage": -0.3706469499999798,
      "average_win": 105.210575650001,
      "average_loss": 247.4858463,
      "expectancy": -12.354898333332685,
      "expectancy_percentage": -0.12354898333332685,
      "expected_net_profit_every_100_trades": -12.354898333332685,
      "average_holding_period": 241200.0,
      "average_winning_holding_period": 147600.0,
      "average_losing_holding_period": 428400.0,
      "gross_profit": 210.421151300002,
      "gross_loss": -247.4858463,
      "max_drawdown": -3.333994706052401,
      "annual_return": -1.4783857643808407,
      "sharpe_ratio": -0.26211956595073843,
      "calmar_ratio": -0.4434277480096288,
      "sortino_ratio": -0.32964650024319886,
      "omega_ratio": 0.8996324367154944,
      "serenity_index": -Infinity,
      "total_open_trades": 0,
      "open_pl": 0.0,
      "winning_streak": 2,
      "losing_streak": 1,
      "largest_losing_trade": -247.4858463,
      "largest_winning_trade": 165.18696850000174,
      "current_streak": -1
    }
  },
  {
    "rank": 14,
    "trial_num": 529,
    "trial_id": 28271,
    "fitness_sharpe": 0.35163567882995905,
    "parameters": {
      "buy_threshold": 35.0,
      "rsi_period": 17.0,
      "sell_threshold": 62.0
    },
    "training_metrics": {
      "total": 10,
      "total_winning_trades": 9,
      "total_losing_trades": 1,
      "starting_balance": 10000.0,
      "finishing_balance": 12194.01620355,
      "win_rate": 0.9,
      "ratio_avg_win_loss": 1.7364793526796753,
      "longs_count": 10,
      "longs_percentage": 100.0,
      "shorts_percentage": 0.0,
      "shorts_count": 0,
      "fee": 113.51749645000001,
      "net_profit": 2194.01620355,
      "net_profit_percentage": 21.940162035499995,
      "average_win": 260.4444908388888,
      "average_loss": 149.98421399999935,
      "expectancy": 219.40162035499998,
      "expectancy_percentage": 2.19401620355,
      "expected_net_profit_every_100_trades": 219.401620355,
      "average_holding_period": 149400.0,
      "average_winning_holding_period": 125200.0,
      "average_losing_holding_period": 367200.0,
      "gross_profit": 2344.000417549999,
      "gross_loss": -149.98421399999935,
      "max_drawdown": -3.856114146944245,
      "annual_return": 49.51559771199461,
      "sharpe_ratio": 3.3679924671295494,
      "calmar_ratio": 12.84080186039953,
      "sortino_ratio": 7.37677173104235,
      "omega_ratio": 4.926230726658691,
      "serenity_index": Infinity,
      "total_open_trades": 0,
      "open_pl": 0.0,
      "winning_streak": 9,
      "losing_streak": 1,
      "largest_losing_trade": -149.98421399999935,
      "largest_winning_trade": 500.20492945000166,
      "current_streak": -1
    },
    "testing_metrics": {
      "total": 3,
      "total_winning_trades": 2,
      "total_losing_trades": 1,
      "starting_balance": 10000.0,
      "finishing_balance": 9962.935304999997,
      "win_rate": 0.6666666666666666,
      "ratio_avg_win_loss": 0.42511754600489654,
      "longs_count": 3,
      "longs_percentage": 100.0,
      "shorts_percentage": 0.0,
      "shorts_count": 0,
      "fee": 29.972295000000003,
      "net_profit": -37.06469499999798,
      "net_profit_percentage": -0.3706469499999798,
      "average_win": 105.210575650001,
      "average_loss": 247.4858463,
      "expectancy": -12.354898333332685,
      "expectancy_percentage": -0.12354898333332685,
      "expected_net_profit_every_100_trades": -12.354898333332685,
      "average_holding_period": 241200.0,
      "average_winning_holding_period": 147600.0,
      "average_losing_holding_period": 428400.0,
      "gross_profit": 210.421151300002,
      "gross_loss": -247.4858463,
      "max_drawdown": -3.333994706052401,
      "annual_return": -1.4783857643808407,
      "sharpe_ratio": -0.26211956595073843,
      "calmar_ratio": -0.4434277480096288,
      "sortino_ratio": -0.32964650024319886,
      "omega_ratio": 0.8996324367154944,
      "serenity_index": -Infinity,
      "total_open_trades": 0,
      "open_pl": 0.0,
      "winning_streak": 2,
      "losing_streak": 1,
      "largest_losing_trade": -247.4858463,
      "largest_winning_trade": 165.18696850000174,
      "current_streak": -1
    }
  },
  {
    "rank": 15,
    "trial_num": 546,
    "trial_id": 28288,
    "fitness_sharpe": 0.35163567882995905,
    "parameters": {
      "buy_threshold": 35.0,
      "rsi_period": 17.0,
      "sell_threshold": 62.0
    },
    "training_metrics": null,
    "testing_metrics": null
  },
  {
    "rank": 16,
    "trial_num": 553,
    "trial_id": 28295,
    "fitness_sharpe": 0.35163567882995905,
    "parameters": {
      "buy_threshold": 35.0,
      "rsi_period": 17.0,
      "sell_threshold": 62.0
    },
    "training_metrics": {
      "total": 10,
      "total_winning_trades": 9,
      "total_losing_trades": 1,
      "starting_balance": 10000.0,
      "finishing_balance": 12194.01620355,
      "win_rate": 0.9,
      "ratio_avg_win_loss": 1.7364793526796753,
      "longs_count": 10,
      "longs_percentage": 100.0,
      "shorts_percentage": 0.0,
      "shorts_count": 0,
      "fee": 113.51749645000001,
      "net_profit": 2194.01620355,
      "net_profit_percentage": 21.940162035499995,
      "average_win": 260.4444908388888,
      "average_loss": 149.98421399999935,
      "expectancy": 219.40162035499998,
      "expectancy_percentage": 2.19401620355,
      "expected_net_profit_every_100_trades": 219.401620355,
      "average_holding_period": 149400.0,
      "average_winning_holding_period": 125200.0,
      "average_losing_holding_period": 367200.0,
      "gross_profit": 2344.000417549999,
      "gross_loss": -149.98421399999935,
      "max_drawdown": -3.856114146944245,
      "annual_return": 49.51559771199461,
      "sharpe_ratio": 3.3679924671295494,
      "calmar_ratio": 12.84080186039953,
      "sortino_ratio": 7.37677173104235,
      "omega_ratio": 4.926230726658691,
      "serenity_index": Infinity,
      "total_open_trades": 0,
      "open_pl": 0.0,
      "winning_streak": 9,
      "losing_streak": 1,
      "largest_losing_trade": -149.98421399999935,
      "largest_winning_trade": 500.20492945000166,
      "current_streak": -1
    },
    "testing_metrics": {
      "total": 3,
      "total_winning_trades": 2,
      "total_losing_trades": 1,
      "starting_balance": 10000.0,
      "finishing_balance": 9962.935304999997,
      "win_rate": 0.6666666666666666,
      "ratio_avg_win_loss": 0.42511754600489654,
      "longs_count": 3,
      "longs_percentage": 100.0,
      "shorts_percentage": 0.0,
      "shorts_count": 0,
      "fee": 29.972295000000003,
      "net_profit": -37.06469499999798,
      "net_profit_percentage": -0.3706469499999798,
      "average_win": 105.210575650001,
      "average_loss": 247.4858463,
      "expectancy": -12.354898333332685,
      "expectancy_percentage": -0.12354898333332685,
      "expected_net_profit_every_100_trades": -12.354898333332685,
      "average_holding_period": 241200.0,
      "average_winning_holding_period": 147600.0,
      "average_losing_holding_period": 428400.0,
      "gross_profit": 210.421151300002,
      "gross_loss": -247.4858463,
      "max_drawdown": -3.333994706052401,
      "annual_return": -1.4783857643808407,
      "sharpe_ratio": -0.26211956595073843,
      "calmar_ratio": -0.4434277480096288,
      "sortino_ratio": -0.32964650024319886,
      "omega_ratio": 0.8996324367154944,
      "serenity_index": -Infinity,
      "total_open_trades": 0,
      "open_pl": 0.0,
      "winning_streak": 2,
      "losing_streak": 1,
      "largest_losing_trade": -247.4858463,
      "largest_winning_trade": 165.18696850000174,
      "current_streak": -1
    }
  },
  {
    "rank": 17,
    "trial_num": 586,
    "trial_id": 28328,
    "fitness_sharpe": 0.35163567882995905,
    "parameters": {
      "buy_threshold": 35.0,
      "rsi_period": 17.0,
      "sell_threshold": 62.0
    },
    "training_metrics": null,
    "testing_metrics": null
  },
  {
    "rank": 18,
    "trial_num": 593,
    "trial_id": 28335,
    "fitness_sharpe": 0.35163567882995905,
    "parameters": {
      "buy_threshold": 35.0,
      "rsi_period": 17.0,
      "sell_threshold": 62.0
    },
    "training_metrics": {
      "total": 10,
      "total_winning_trades": 9,
      "total_losing_trades": 1,
      "starting_balance": 10000.0,
      "finishing_balance": 12194.01620355,
      "win_rate": 0.9,
      "ratio_avg_win_loss": 1.7364793526796753,
      "longs_count": 10,
      "longs_percentage": 100.0,
      "shorts_percentage": 0.0,
      "shorts_count": 0,
      "fee": 113.51749645000001,
      "net_profit": 2194.01620355,
      "net_profit_percentage": 21.940162035499995,
      "average_win": 260.4444908388888,
      "average_loss": 149.98421399999935,
      "expectancy": 219.40162035499998,
      "expectancy_percentage": 2.19401620355,
      "expected_net_profit_every_100_trades": 219.401620355,
      "average_holding_period": 149400.0,
      "average_winning_holding_period": 125200.0,
      "average_losing_holding_period": 367200.0,
      "gross_profit": 2344.000417549999,
      "gross_loss": -149.98421399999935,
      "max_drawdown": -3.856114146944245,
      "annual_return": 49.51559771199461,
      "sharpe_ratio": 3.3679924671295494,
      "calmar_ratio": 12.84080186039953,
      "sortino_ratio": 7.37677173104235,
      "omega_ratio": 4.926230726658691,
      "serenity_index": Infinity,
      "total_open_trades": 0,
      "open_pl": 0.0,
      "winning_streak": 9,
      "losing_streak": 1,
      "largest_losing_trade": -149.98421399999935,
      "largest_winning_trade": 500.20492945000166,
      "current_streak": -1
    },
    "testing_metrics": {
      "total": 3,
      "total_winning_trades": 2,
      "total_losing_trades": 1,
      "starting_balance": 10000.0,
      "finishing_balance": 9962.935304999997,
      "win_rate": 0.6666666666666666,
      "ratio_avg_win_loss": 0.42511754600489654,
      "longs_count": 3,
      "longs_percentage": 100.0,
      "shorts_percentage": 0.0,
      "shorts_count": 0,
      "fee": 29.972295000000003,
      "net_profit": -37.06469499999798,
      "net_profit_percentage": -0.3706469499999798,
      "average_win": 105.210575650001,
      "average_loss": 247.4858463,
      "expectancy": -12.354898333332685,
      "expectancy_percentage": -0.12354898333332685,
      "expected_net_profit_every_100_trades": -12.354898333332685,
      "average_holding_period": 241200.0,
      "average_winning_holding_period": 147600.0,
      "average_losing_holding_period": 428400.0,
      "gross_profit": 210.421151300002,
      "gross_loss": -247.4858463,
      "max_drawdown": -3.333994706052401,
      "annual_return": -1.4783857643808407,
      "sharpe_ratio": -0.26211956595073843,
      "calmar_ratio": -0.4434277480096288,
      "sortino_ratio": -0.32964650024319886,
      "omega_ratio": 0.8996324367154944,
      "serenity_index": -Infinity,
      "total_open_trades": 0,
      "open_pl": 0.0,
      "winning_streak": 2,
      "losing_streak": 1,
      "largest_losing_trade": -247.4858463,
      "largest_winning_trade": 165.18696850000174,
      "current_streak": -1
    }
  },
  {
    "rank": 19,
    "trial_num": 326,
    "trial_id": 28068,
    "fitness_sharpe": 0.3502162331047265,
    "parameters": {
      "buy_threshold": 35.0,
      "rsi_period": 17.0,
      "sell_threshold": 63.0
    },
    "training_metrics": null,
    "testing_metrics": null
  },
  {
    "rank": 20,
    "trial_num": 328,
    "trial_id": 28070,
    "fitness_sharpe": 0.3502162331047265,
    "parameters": {
      "buy_threshold": 35.0,
      "rsi_period": 17.0,
      "sell_threshold": 63.0
    },
    "training_metrics": null,
    "testing_metrics": null
  }
]